tracktorlive/__init__.py
tracktorlive/__main__.py
tracktorlive/client.py
tracktorlive/memorymanagement.py
tracktorlive/paramfixing.py
tracktorlive/server.py
tracktorlive/sync.py
tracktorlive/tracktor.py
tracktorlive/trackutils.py
tracktorlive/videoout.py
tracktorlive-0.1.0.dist-info/METADATA
tracktorlive-0.1.0.dist-info/WHEEL
tracktorlive-0.1.0.dist-info/entry_points.txt
tracktorlive-0.1.0.dist-info/top_level.txt
tracktorlive-0.1.0.dist-info/RECORD
