Metadata-Version: 2.4
Name: tracktorlive
Version: 0.1.0
Summary: Real-time low-cost animal tracking and response delivery.
Author: Dominique Roche, Isaac Planas-Sitjà, Pranav Minasandra, Vivek H Sridhar
Requires-Python: >=3.8
Requires-Dist: opencv-python
Requires-Dist: numpy<2.0
Requires-Dist: platformdirs
Requires-Dist: python-ulid
Requires-Dist: scikit-learn
